Workbook

Sheet Catálogo
A1: CATÁLOGO DE PRODUCTOS — ARPAPEL (MAQUILA)
A2: Kattegat Packing SA de CV — Productos coextruidos
A4: Clave | B4: Descripción Comercial | C4: Papel (g/m²) | D4: PE (g/m²) | E4: Gramaje Total (g/m²) | F4: Precio Venta (MXN/M²) | G4: Tipo Maquila
A5: AP0032 | B5: Tela Coextruida Blanca | C5: 62 | D5: 18 | E5: 80 | F5: 4.15 | G5: Coextrusión
A6: AP0033 | B6: Coextruido BOND 70+PE 10 | C6: 70 | D6: 10 | E6: 80 | F6: 3.7 | G6: Coextrusión
A7: AP0034 | B7: Coextruido KRAFT 130+PE 14 | C7: 130 | D7: 14 | E7: 144 | F7: 4.2 | G7: Coextrusión
A8: AP0035 | B8: Coextruido BOND 32.5+PE 15 | C8: 32.5 | D8: 15 | E8: 47 | F8: 2 | G8: Coextrusión
A9: AP0038 | B9: Coextruido LWC 60+PE 18 | C9: 60 | D9: 18 | E9: 78 | F9: 1.4 | G9: Coextrusión
A10: AP0039 | B10: Coextruido BOND 90+PEBD 15 | C10: 90 | D10: 15 | E10: 105 | F10: 5.5 | G10: Coextrusión
A13: SUPUESTOS DE COSTO
A14: Costo PEBD (USD/kg) | B14: 1.5
A15: Tipo de Cambio (MXN/USD) | B15: 20.5
A16: Costo PEBD (MXN/kg) | B16: =B14*B15 -> 30.75
A17: Costo Conversión (MXN/M²) | B17: 0.3 | C17: (energía, mano de obra, overhead)

Sheet Márgenes
A1: ANÁLISIS DE MÁRGENES POR PRODUCTO — MAQUILA ARPAPEL
A2: Papel = $0 (lo pone Arpapel) | Costo Kattegat = PE + Conversión
A4: Clave | B4: Descripción | C4: PE (g/m²) | D4: PE Cost (MXN/M²) | E4: Conversión (MXN/M²) | F4: Costo Total (MXN/M²) | G4: Precio Venta (MXN/M²) | H4: Margen (MXN/M²) | I4: Margen % | J4: Rentabilidad
A5: AP0032 | B5: Tela Coextruida Blanca | C5: 18 | D5: =C5/1000*Catálogo!B16 -> 0.5535 | E5: =Catálogo!B17 -> 0.3 | F5: =D5+E5 -> 0.8535 | G5: =Catálogo!F5 -> 4.15 | H5: =G5-F5 -> 3.2965 | I5: =IF(G5>0,H5/G5,0) -> 0.79433735 | J5: =IF(I5>0.5,"⭐⭐⭐",IF(I5>0.3,"⭐⭐","⭐")) -> ⭐⭐⭐
A6: AP0033 | B6: Coextruido BOND 70+PE 10 | C6: 10 | D6: =C6/1000*Catálogo!B16 -> 0.3075 | E6: =Catálogo!B17 -> 0.3 | F6: =D6+E6 -> 0.6075 | G6: =Catálogo!F6 -> 3.7 | H6: =G6-F6 -> 3.0925 | I6: =IF(G6>0,H6/G6,0) -> 0.83581081 | J6: =IF(I6>0.5,"⭐⭐⭐",IF(I6>0.3,"⭐⭐","⭐")) -> ⭐⭐⭐
A7: AP0034 | B7: Coextruido KRAFT 130+PE 14 | C7: 14 | D7: =C7/1000*Catálogo!B16 -> 0.4305 | E7: =Catálogo!B17 -> 0.3 | F7: =D7+E7 -> 0.7305 | G7: =Catálogo!F7 -> 4.2 | H7: =G7-F7 -> 3.4695 | I7: =IF(G7>0,H7/G7,0) -> 0.82607143 | J7: =IF(I7>0.5,"⭐⭐⭐",IF(I7>0.3,"⭐⭐","⭐")) -> ⭐⭐⭐
A8: AP0035 | B8: Coextruido BOND 32.5+PE 15 | C8: 15 | D8: =C8/1000*Catálogo!B16 -> 0.46125 | E8: =Catálogo!B17 -> 0.3 | F8: =D8+E8 -> 0.76125 | G8: =Catálogo!F8 -> 2 | H8: =G8-F8 -> 1.23875 | I8: =IF(G8>0,H8/G8,0) -> 0.619375 | J8: =IF(I8>0.5,"⭐⭐⭐",IF(I8>0.3,"⭐⭐","⭐")) -> ⭐⭐⭐
A9: AP0038 | B9: Coextruido LWC 60+PE 18 | C9: 18 | D9: =C9/1000*Catálogo!B16 -> 0.5535 | E9: =Catálogo!B17 -> 0.3 | F9: =D9+E9 -> 0.8535 | G9: =Catálogo!F9 -> 1.4 | H9: =G9-F9 -> 0.5465 | I9: =IF(G9>0,H9/G9,0) -> 0.39035714 | J9: =IF(I9>0.5,"⭐⭐⭐",IF(I9>0.3,"⭐⭐","⭐")) -> ⭐⭐
A10: AP0039 | B10: Coextruido BOND 90+PEBD 15 | C10: 15 | D10: =C10/1000*Catálogo!B16 -> 0.46125 | E10: =Catálogo!B17 -> 0.3 | F10: =D10+E10 -> 0.76125 | G10: =Catálogo!F10 -> 5.5 | H10: =G10-F10 -> 4.73875 | I10: =IF(G10>0,H10/G10,0) -> 0.86159091 | J10: =IF(I10>0.5,"⭐⭐⭐",IF(I10>0.3,"⭐⭐","⭐")) -> ⭐⭐⭐

Sheet Historial
A1: HISTORIAL DE VENTAS KATTEGAT → ARPAPEL (2025-2026)
A3: Mes | B3: Factura | C3: PO (ODC) | D3: Clave | E3: Descripción | F3: Cantidad M² | G3: P.U. (MXN/M²) | H3: Subtotal MXN | I3: Total c/IVA | J3: TC MXN/USD | K3: Costo PE (MXN) | L3: Utilidad Bruta
A4: Ene 2025 | B4: 90 | C4: PO59493 | D4: AP0035 | E4: COEXTRUIDO BOND32.5R+PE15GR 47GR | F4: 13064 | G4: 2 | H4: =F4*G4 -> 26128 | I4: =H4*1.16 -> 30308.48 | J4: 20.3 | K4: =F4*15/1000*Catálogo!B14*J4+F4*Catálogo!B17 -> 9886.182 | L4: =H4-K4 -> 16241.818
A5: Ene 2025 | B5: 91 | C5: PO59494 | D5: AP0035 | E5: COEXTRUIDO BOND32.5R+PE15GR 47GR | F5: 59984 | G5: 2 | H5: =F5*G5 -> 119968 | I5: =H5*1.16 -> 139162.88 | J5: 20.3 | K5: =F5*15/1000*Catálogo!B14*J5+F5*Catálogo!B17 -> 45392.892 | L5: =H5-K5 -> 74575.108
A6: Ene 2025 | B6: 92 | C6: PO59363 | D6: AP0035 | E6: COEXTRUIDO BOND32.5R+PE15GR 47GR | F6: 30400 | G6: 2 | H6: =F6*G6 -> 60800 | I6: =H6*1.16 -> 70528 | J6: 20.3 | K6: =F6*15/1000*Catálogo!B14*J6+F6*Catálogo!B17 -> 23005.2 | L6: =H6-K6 -> 37794.8
A7: Ene 2025 | B7: 93 | C7: PO59583 | D7: AP0033 | E7: COEXTRUIDO BOND70GR+PE10GR 80GR | F7: 38308 | G7: 3.7 | H7: =F7*G7 -> 141739.6 | I7: =H7*1.16 -> 164417.94 | J7: 20.3 | K7: =F7*10/1000*Catálogo!B14*J7+F7*Catálogo!B17 -> 23157.186 | L7: =H7-K7 -> 118582.41
A8: Feb 2025 | B8: 95 | C8: PO60181 | D8: AP0033 | E8: COEXTRUIDO BOND70GR+PE10GR 80GR | F8: 41572.5 | G8: 3.7 | H8: =F8*G8 -> 153818.25 | I8: =H8*1.16 -> 178429.17 | J8: 20.4 | K8: =F8*10/1000*Catálogo!B14*J8+F8*Catálogo!B17 -> 25192.935 | L8: =H8-K8 -> 128625.32
A9: Abr 2025 | B9: 96 | C9: PO60899 | D9: AP0033 | E9: COEXTRUIDO BOND70GR+PE10GR 80GR | F9: 27600 | G9: 3.7 | H9: =F9*G9 -> 102120 | I9: =H9*1.16 -> 118459.2 | J9: 19.8 | K9: =F9*10/1000*Catálogo!B14*J9+F9*Catálogo!B17 -> 16477.2 | L9: =H9-K9 -> 85642.8
A10: Abr 2025 | B10: 97 | C10: PO61175 | D10: AP0033 | E10: COEXTRUIDO BOND70GR+PE10GR 80GR | F10: 39330 | G10: 3.7 | H10: =F10*G10 -> 145521 | I10: =H10*1.16 -> 168804.36 | J10: 19.8 | K10: =F10*10/1000*Catálogo!B14*J10+F10*Catálogo!B17 -> 23480.01 | L10: =H10-K10 -> 122040.99
A11: May 2025 | B11: 98 | C11: PO61873 | D11: AP0032 | E11: TELA COEXTRUIDA BLANCA 80GR | F11: 19730.7 | G11: 4.15 | H11: =F11*G11 -> 81882.405 | I11: =H11*1.16 -> 94983.59 | J11: 19.5 | K11: =F11*18/1000*Catálogo!B14*J11+F11*Catálogo!B17 -> 16307.424 | L11: =H11-K11 -> 65574.981
A12: Jun 2025 | B12: 100 | C12: PO62588 | D12: AP0033/AP0035 | E12: BOND70+PE10 + BOND32.5+PE15 | F12: 177552.5 | G12: 2.67 | H12: =F12*G12 -> 474065.17 | I12: =H12*1.16 -> 549915.6 | J12: 19.7 | K12: =F12*10/1000*Catálogo!B14*J12+F12*Catálogo!B17 -> 105732.51 | L12: =H12-K12 -> 368332.66
A13: Jun 2025 | B13: 101 | C13: PO62294 | D13: AP0038 | E13: COEXTRUIDO LWC60GR+PE18GR 78GR | F13: 61300 | G13: 1.4 | H13: =F13*G13 -> 85820 | I13: =H13*1.16 -> 99551.2 | J13: 19.7 | K13: =F13*18/1000*Catálogo!B14*J13+F13*Catálogo!B17 -> 50995.47 | L13: =H13-K13 -> 34824.53
A14: Jun 2025 | B14: 102 | C14: PO62295 | D14: AP0035 | E14: COEXTRUIDO BOND32.5R+PE15GR 47GR | F14: 70300 | G14: 2 | H14: =F14*G14 -> 140600 | I14: =H14*1.16 -> 163096 | J14: 19.7 | K14: =F14*15/1000*Catálogo!B14*J14+F14*Catálogo!B17 -> 52250.475 | L14: =H14-K14 -> 88349.525
A15: Jul 2025 | B15: 103 | C15: PO62954 | D15: AP0039 | E15: COEXTRUIDO BOND90GR+PEBD15GR 105GR | F15: 89100 | G15: 5.5 | H15: =F15*G15 -> 490050 | I15: =H15*1.16 -> 568458 | J15: 19.9 | K15: =F15*15/1000*Catálogo!B14*J15+F15*Catálogo!B17 -> 66624.525 | L15: =H15-K15 -> 423425.47
A16: Jul 2025 | B16: 104 | C16: PO63188 | D16: AP0035 | E16: COEXTRUIDO BOND32.5R+PE15GR 47GR | F16: 85690 | G16: 2 | H16: =F16*G16 -> 171380 | I16: =H16*1.16 -> 198800.8 | J16: 19.9 | K16: =F16*15/1000*Catálogo!B14*J16+F16*Catálogo!B17 -> 64074.698 | L16: =H16-K16 -> 107305.3
A17: Ago 2025 | B17: 106 | C17: PO63645 | D17: AP0034 | E17: COEXTRUIDO KRAFT130GR+PE14GR 144GR | F17: 5310 | G17: 4.2 | H17: =F17*G17 -> 22302 | I17: =H17*1.16 -> 25870.32 | J17: 20 | K17: =F17*14/1000*Catálogo!B14*J17+F17*Catálogo!B17 -> 3823.2 | L17: =H17-K17 -> 18478.8
A18: Ago 2025 | B18: 108 | C18: PO63889 | D18: AP0033/AP0038 | E18: BOND70+PE10 + LWC60+PE18 | F18: 82022.5 | G18: 3.31 | H18: =F18*G18 -> 271494.47 | I18: =H18*1.16 -> 314933.59 | J18: 20 | K18: =F18*10/1000*Catálogo!B14*J18+F18*Catálogo!B17 -> 49213.5 | L18: =H18-K18 -> 222280.98
A19: Sep 2025 | B19: 109 | C19: PO63934 | D19: AP0035 | E19: COEXTRUIDO BOND32.5R+PE15GR 47GR | F19: 57190 | G19: 2 | H19: =F19*G19 -> 114380 | I19: =H19*1.16 -> 132680.8 | J19: 19.8 | K19: =F19*15/1000*Catálogo!B14*J19+F19*Catálogo!B17 -> 42635.145 | L19: =H19-K19 -> 71744.855
A20: Sep 2025 | B20: 110 | C20: PO64084 | D20: AP0033 | E20: COEXTRUIDO BOND70GR+PE10GR 80GR | F20: 86480 | G20: 3.7 | H20: =F20*G20 -> 319976 | I20: =H20*1.16 -> 371172.16 | J20: 19.8 | K20: =F20*10/1000*Catálogo!B14*J20+F20*Catálogo!B17 -> 51628.56 | L20: =H20-K20 -> 268347.44
A21: Sep 2025 | B21: 111 | C21: PO64218 | D21: AP0034 | E21: COEXTRUIDO KRAFT130GR+PE14GR 144GR | F21: 14900 | G21: 4.2 | H21: =F21*G21 -> 62580 | I21: =H21*1.16 -> 72592.8 | J21: 19.8 | K21: =F21*14/1000*Catálogo!B14*J21+F21*Catálogo!B17 -> 10665.42 | L21: =H21-K21 -> 51914.58
A22: Oct 2025 | B22: 112 | C22: PO64528 | D22: AP0034 | E22: COEXTRUIDO KRAFT130GR+PE14GR 144GR | F22: 39159 | G22: 4.2 | H22: =F22*G22 -> 164467.8 | I22: =H22*1.16 -> 190782.65 | J22: 20.1 | K22: =F22*14/1000*Catálogo!B14*J22+F22*Catálogo!B17 -> 28276.714 | L22: =H22-K22 -> 136191.09
A23: Oct 2025 | B23: 113 | C23: PO64529 | D23: AP0033/AP0035 | E23: BOND70+PE10 + BOND32.5+PE15 | F23: 60660 | G23: 3.3 | H23: =F23*G23 -> 200178 | I23: =H23*1.16 -> 232206.48 | J23: 20.1 | K23: =F23*10/1000*Catálogo!B14*J23+F23*Catálogo!B17 -> 36486.99 | L23: =H23-K23 -> 163691.01
A24: Oct 2025 | B24: 114 | C24: PO64624 | D24: AP0035 | E24: COEXTRUIDO BOND32.5R+PE15GR 47GR | F24: 28405 | G24: 2 | H24: =F24*G24 -> 56810 | I24: =H24*1.16 -> 65899.6 | J24: 20.1 | K24: =F24*15/1000*Catálogo!B14*J24+F24*Catálogo!B17 -> 21367.661 | L24: =H24-K24 -> 35442.339
A25: Oct 2025 | B25: 115 | C25: PO64808 | D25: AP0035 | E25: COEXTRUIDO BOND32.5R+PE15GR 47GR | F25: 90060 | G25: 2 | H25: =F25*G25 -> 180120 | I25: =H25*1.16 -> 208939.2 | J25: 20.1 | K25: =F25*15/1000*Catálogo!B14*J25+F25*Catálogo!B17 -> 67747.635 | L25: =H25-K25 -> 112372.37
A26: Oct 2025 | B26: 116 | C26: PO64809 | D26: AP0033 | E26: COEXTRUIDO BOND70GR+PE10GR 80GR | F26: 45655 | G26: 3.7 | H26: =F26*G26 -> 168923.5 | I26: =H26*1.16 -> 195951.26 | J26: 20.1 | K26: =F26*10/1000*Catálogo!B14*J26+F26*Catálogo!B17 -> 27461.482 | L26: =H26-K26 -> 141462.02
A27: Oct 2025 | B27: 117 | C27: PO64832 | D27: AP0035 | E27: COEXTRUIDO BOND32.5R+PE15GR 47GR | F27: 28500 | G27: 2 | H27: =F27*G27 -> 57000 | I27: =H27*1.16 -> 66120 | J27: 20.1 | K27: =F27*15/1000*Catálogo!B14*J27+F27*Catálogo!B17 -> 21439.125 | L27: =H27-K27 -> 35560.875
A28: Oct 2025 | B28: 118 | C28: PO64934 | D28: AP0035 | E28: COEXTRUIDO BOND32.5R+PE15GR 47GR | F28: 28215 | G28: 2 | H28: =F28*G28 -> 56430 | I28: =H28*1.16 -> 65458.8 | J28: 20.1 | K28: =F28*15/1000*Catálogo!B14*J28+F28*Catálogo!B17 -> 21224.734 | L28: =H28-K28 -> 35205.266
A29: Oct 2025 | B29: 119 | C29: PO64935 | D29: AP0035 | E29: COEXTRUIDO BOND32.5R+PE15GR 47GR | F29: 9500 | G29: 2 | H29: =F29*G29 -> 19000 | I29: =H29*1.16 -> 22040 | J29: 20.1 | K29: =F29*15/1000*Catálogo!B14*J29+F29*Catálogo!B17 -> 7146.375 | L29: =H29-K29 -> 11853.625
A30: Oct 2025 | B30: 120 | C30: PO64936 | D30: AP0035 | E30: COEXTRUIDO BOND32.5R+PE15GR 47GR | F30: 28025 | G30: 2 | H30: =F30*G30 -> 56050 | I30: =H30*1.16 -> 65018 | J30: 20.1 | K30: =F30*15/1000*Catálogo!B14*J30+F30*Catálogo!B17 -> 21081.806 | L30: =H30-K30 -> 34968.194
A31: Nov 2025 | B31: 121 | C31: PO65011 | D31: AP0035 | E31: COEXTRUIDO BOND32.5R+PE15GR 47GR | F31: 28025 | G31: 2 | H31: =F31*G31 -> 56050 | I31: =H31*1.16 -> 65018 | J31: 20.3 | K31: =F31*15/1000*Catálogo!B14*J31+F31*Catálogo!B17 -> 21207.919 | L31: =H31-K31 -> 34842.081
A32: Nov 2025 | B32: 122 | C32: PO65059 | D32: AP0035 | E32: COEXTRUIDO BOND32.5R+PE15GR 47GR | F32: 28120 | G32: 2 | H32: =F32*G32 -> 56240 | I32: =H32*1.16 -> 65238.4 | J32: 20.3 | K32: =F32*15/1000*Catálogo!B14*J32+F32*Catálogo!B17 -> 21279.81 | L32: =H32-K32 -> 34960.19
A33: Nov 2025 | B33: 125 | C33: PO65152 | D33: AP0033/AP0035 | E33: BOND70+PE10 + BOND32.5+PE15 | F33: 69934.5 | G33: 2.89 | H33: =F33*G33 -> 202110.7 | I33: =H33*1.16 -> 234448.42 | J33: 20.3 | K33: =F33*10/1000*Catálogo!B14*J33+F33*Catálogo!B17 -> 42275.405 | L33: =H33-K33 -> 159835.3
A34: Nov 2025 | B34: 126 | C34: PO65309 | D34: AP0035 | E34: COEXTRUIDO BOND32.5R+PE15GR 47GR | F34: 51585 | G34: 2 | H34: =F34*G34 -> 103170 | I34: =H34*1.16 -> 119677.2 | J34: 20.3 | K34: =F34*15/1000*Catálogo!B14*J34+F34*Catálogo!B17 -> 39036.949 | L34: =H34-K34 -> 64133.051
A35: Nov 2025 | B35: 127 | C35: PO65456 | D35: AP0035 | E35: COEXTRUIDO BOND32.5R+PE15GR 47GR | F35: 31397.5 | G35: 2 | H35: =F35*G35 -> 62795 | I35: =H35*1.16 -> 72842.2 | J35: 20.3 | K35: =F35*15/1000*Catálogo!B14*J35+F35*Catálogo!B17 -> 23760.058 | L35: =H35-K35 -> 39034.942
A36: Dic 2025 | B36: 129 | C36: PO65669 | D36: AP0035 | E36: COEXTRUIDO BOND32.5R+PE15GR 47GR | F36: 50302.5 | G36: 2 | H36: =F36*G36 -> 100605 | I36: =H36*1.16 -> 116701.8 | J36: 20.5 | K36: =F36*15/1000*Catálogo!B14*J36+F36*Catálogo!B17 -> 38292.778 | L36: =H36-K36 -> 62312.222
A37: Dic 2025 | B37: 130 | C37: PO65662 | D37: AP0033 | E37: COEXTRUIDO BOND70GR+PE10GR 80GR | F37: 130352.5 | G37: 3.7 | H37: =F37*G37 -> 482304.25 | I37: =H37*1.16 -> 559472.93 | J37: 20.5 | K37: =F37*10/1000*Catálogo!B14*J37+F37*Catálogo!B17 -> 79189.144 | L37: =H37-K37 -> 403115.11
A38: Ene 2026 | B38: 131 | C38: PO66064 | D38: AP0034 | E38: COEXTRUIDO KRAFT130GR+PE14GR 144GR | F38: 38619 | G38: 4.2 | H38: =F38*G38 -> 162199.8 | I38: =H38*1.16 -> 188151.77 | J38: 20.4 | K38: =F38*14/1000*Catálogo!B14*J38+F38*Catálogo!B17 -> 28130.08 | L38: =H38-K38 -> 134069.72
A39: Feb 2026 | B39: - | C39: PO66782 | D39: AP0039 | E39: COEXTRUIDO BOND90GR+PEBD15GR 105GR | F39: 145000 | G39: 5.5 | H39: =F39*G39 -> 797500 | I39: =H39*1.16 -> 925100 | J39: 20.5 | K39: =F39*15/1000*Catálogo!B14*J39+F39*Catálogo!B17 -> 110381.25 | L39: =H39-K39 -> 687118.75
E40: TOTALES | F40: =SUM(F4:F39) -> 1931349.2 | H40: =SUM(H4:H39) -> 5966579 | I40: =SUM(I4:I39) -> 6921231.6 | K40: =SUM(K4:K39) -> 1336328.4 | L40: =SUM(L4:L39) -> 4630250.5
K41: Margen Global: | L41: =L40/H40 -> 0.77603105

Sheet Resumen Mensual
A1: RESUMEN MENSUAL — FACTURACIÓN Y MÁRGENES
A3: Mes | B3: # Facturas | C3: M² Totales | D3: Facturado (MXN) | E3: Costo PE (MXN) | F3: Utilidad Bruta | G3: Margen % | H3: TC Promedio
A4: Ene 2025 | B4: 4 | C4: 141756 | D4: 348635.6 | E4: 98640.91 | F4: =D4-E4 -> 249994.69 | G4: =IF(D4>0,F4/D4,0) -> 0.71706587 | H4: 20.3
A5: Feb 2025 | B5: 1 | C5: 41572.5 | D5: 153818.25 | E5: 29009.29 | F5: =D5-E5 -> 124808.96 | G5: =IF(D5>0,F5/D5,0) -> 0.81140541 | H5: 20.4
A6: Abr 2025 | B6: 2 | C6: 66930 | D6: 247641 | E6: 45920.67 | F6: =D6-E6 -> 201720.33 | G6: =IF(D6>0,F6/D6,0) -> 0.81456758 | H6: 19.8
A7: May 2025 | B7: 1 | C7: 19730.7 | D7: 81882.405 | E7: 13421.81 | F7: =D7-E7 -> 68460.595 | G7: =IF(D7>0,F7/D7,0) -> 0.83608432 | H7: 19.5
A8: Jun 2025 | B8: 3 | C8: 309152.5 | D8: 700485.18 | E8: 211506.68 | F8: =D8-E8 -> 488978.49 | G8: =IF(D8>0,F8/D8,0) -> 0.69805688 | H8: 19.7
A9: Jul 2025 | B9: 2 | C9: 174790 | D9: 661430 | E9: 120264.26 | F9: =D9-E9 -> 541165.74 | G9: =IF(D9>0,F9/D9,0) -> 0.81817538 | H9: 19.9
A10: Ago 2025 | B10: 2 | C10: 87332.5 | D10: 293796.47 | E10: 60259.42 | F10: =D10-E10 -> 233537.05 | G10: =IF(D10>0,F10/D10,0) -> 0.794894 | H10: 20
A11: Sep 2025 | B11: 3 | C11: 158570 | D11: 496936 | E11: 108794.88 | F11: =D11-E11 -> 388141.12 | G11: =IF(D11>0,F11/D11,0) -> 0.78106863 | H11: 19.8
A12: Oct 2025 | B12: 9 | C12: 358179 | D12: 958979.3 | E12: 247841.96 | F12: =D12-E12 -> 711137.34 | G12: =IF(D12>0,F12/D12,0) -> 0.74155651 | H12: 20.1
A13: Nov 2025 | B13: 5 | C13: 209062 | D13: 480365.71 | E13: 145475.79 | F13: =D13-E13 -> 334889.91 | G13: =IF(D13>0,F13/D13,0) -> 0.69715617 | H13: 20.3
A14: Dic 2025 | B14: 2 | C14: 180655 | D14: 582909.25 | E14: 126413.34 | F14: =D14-E14 -> 456495.91 | G14: =IF(D14>0,F14/D14,0) -> 0.78313376 | H14: 20.5
A15: Ene 2026 | B15: 1 | C15: 38619 | D15: 162199.8 | E15: 26948.34 | F15: =D15-E15 -> 135251.46 | G15: =IF(D15>0,F15/D15,0) -> 0.83385713 | H15: 20.4
A16: Feb 2026 | B16: 1 | C16: 145000 | D16: 797500 | E16: 101463.75 | F16: =D16-E16 -> 696036.25 | G16: =IF(D16>0,F16/D16,0) -> 0.87277273 | H16: 20.5
A17: TOTAL 2025-2026 | B17: =SUM(B4:B16) -> 36 | C17: =SUM(C4:C16) -> 1931349.2 | D17: =SUM(D4:D16) -> 5966579 | E17: =SUM(E4:E16) -> 1335961.1 | F17: =SUM(F4:F16) -> 4630617.9 | G17: =IF(D17>0,F17/D17,0) -> 0.77609261

Sheet Mix Producto
A1: MIX DE PRODUCTO — VOLUMEN Y REVENUE POR ARTÍCULO
A3: Clave | B3: Descripción | C3: M² Totales | D3: % del Volumen | E3: Revenue MXN | F3: % del Revenue | G3: P.U. Promedio
A4: AP0033 | B4: COEXTRUIDO BOND70GR+PE10GR 80GR | C4: 409298 | D4: 0.26557448 | E4: 1514402.6 | F4: 0.31427418 | G4: 3.7
A5: AP0035 | B5: COEXTRUIDO BOND32.5R+PE15GR 47GR | C5: 718763 | D5: 0.46637196 | E5: 1437526 | F5: 0.29832047 | G5: 2
A6: AP0039 | B6: COEXTRUIDO BOND90GR+PEBD15GR 105GR | C6: 234100 | D6: 0.15189663 | E6: 1287550 | F6: 0.26719692 | G6: 5.5
A7: AP0034 | B7: COEXTRUIDO KRAFT130GR+PE14GR 144GR | C7: 97988 | D7: 0.063579867 | E7: 411549.6 | F7: 0.085406227 | G7: 4.2
A8: AP0038 | B8: COEXTRUIDO LWC60GR+PE18GR 78GR | C8: 61300 | D8: 0.039774726 | E8: 85820 | F8: 0.01780967 | G8: 1.4
A9: AP0032 | B9: TELA COEXTRUIDA BLANCA 80GR | C9: 19731 | D9: 0.012802336 | E9: 81882.41 | F9: 0.016992526 | G9: 4.15
A10: TOTAL | C10: 1541180 | D10: 1 | E10: 4818730.6 | F10: 1
